tox_monorepo/__init__.py
tox_monorepo/monorepo.py
tox_monorepo/version.py
tox_monorepo-0.1.1.dist-info/METADATA
tox_monorepo-0.1.1.dist-info/WHEEL
tox_monorepo-0.1.1.dist-info/entry_points.txt
tox_monorepo-0.1.1.dist-info/top_level.txt
tox_monorepo-0.1.1.dist-info/RECORD
