Metadata-Version: 2.1
Name: tox-monorepo
Version: 0.1.1
Summary: A tox plugin built to allow sharing of a common tox.ini file across repositories with high package counts.
Home-page: https://github.com/Azure/azure-sdk-tools/
Author: Microsoft Corporation
Author-email: azuresdkengsysadmins@microsoft.com
License: MIT License
Platform: UNKNOWN
Classifier: Framework :: tox
Classifier: Development Status :: 3 - Alpha
Classifier: Programming Language :: Python
Classifier: Programming Language :: Python :: 2.7
Classifier: Programming Language :: Python :: 3
Classifier: Programming Language :: Python :: 3.4
Classifier: Programming Language :: Python :: 3.5
Classifier: Programming Language :: Python :: 3.6
Classifier: Programming Language :: Python :: 3.7
Classifier: License :: OSI Approved :: MIT License
Requires-Dist: tox (>=3.12.0)
